Metadata-Version: 1.1
Name: rdbgenerate
Version: 0.1.2
Summary: Generate Redis dump files (.rdb) from native Python objects
Home-page: https://github.com/ae-foster/rdbgenerate
Author: ae-foster
Author-email: UNKNOWN
License: GNU General Public License v3 (GPLv3)
Download-URL: https://github.com/ae-foster/rdbgenerate/archive/v0.1.2.tar.gz
Keywords: database,redis,rdb
Platform: UNKNOWN
Classifier: Development Status :: 3 - Alpha
Classifier: Intended Audience :: Developers
Classifier: Topic :: Database
Classifier: License :: OSI Approved :: GNU General Public License v3 (GPLv3)
Classifier: Programming Language :: Python :: 3.3
Classifier: Programming Language :: Python :: 3.4
Classifier: Programming Language :: Python :: 3.5
Classifier: Programming Language :: Python :: 3.6
